fastinit/__init__.py
fastinit/cli.py
fastainit-0.1.0.dist-info/METADATA
fastainit-0.1.0.dist-info/WHEEL
fastainit-0.1.0.dist-info/entry_points.txt
fastainit-0.1.0.dist-info/top_level.txt
fastainit-0.1.0.dist-info/RECORD
