Metadata-Version: 2.4
Name: fastainit
Version: 0.1.0
Summary: CLI simples para gerar projetos e módulos FastAPI
Author-email: João Pedro de Oliveira Matos <joaopedrooliveira030506@gmail.com>
Requires-Python: >=3.8
